ocs_sample_library_preview/__init__.py
ocs_sample_library_preview-0.7.1rc0.dist-info/LICENSE
ocs_sample_library_preview-0.7.1rc0.dist-info/METADATA
ocs_sample_library_preview-0.7.1rc0.dist-info/WHEEL
ocs_sample_library_preview-0.7.1rc0.dist-info/top_level.txt
ocs_sample_library_preview-0.7.1rc0.dist-info/RECORD
