Metadata-Version: 2.1
Name: ocs-sample-library-preview
Version: 0.7.1rc0
Summary: A preview of an OCS (OSIsoft Cloud Services) client library. Note: This library has been deprecated in favor of the AVEVA Data Hub library at https://pypi.org/project/adh-sample-library-preview/
Home-page: https://github.com/osisoft/sample-ocs-sample_libraries-python
Author: OSIsoft
Author-email: dendres@osisoft.com
License: Apache 2.0
Platform: UNKNOWN
Classifier: Programming Language :: Python :: 3
Classifier: License :: OSI Approved :: Apache Software License
Classifier: Operating System :: OS Independent
Classifier: Development Status :: 7 - Inactive
Requires-Python: >=3.7
Requires-Dist: adh-sample-library-preview (>=0.7.1rc0)
